[
  {
    "table_catalog":"angad_kumar91",
    "table_schema":"information_schema",
    "table_name":"tables",
    "table_type":"VIEW",
    "created":1765009795927
  },
  {
    "table_catalog":"angad_kumar91",
    "table_schema":"information_schema",
    "table_name":"referential_constraints",
    "table_type":"VIEW",
    "created":1765009795707
  },
  {
    "table_catalog":"angad_kumar91",
    "table_schema":"information_schema",
    "table_name":"views",
    "table_type":"VIEW",
    "created":1765009795948
  },
  {
    "table_catalog":"angad_kumar91",
    "table_schema":"information_schema",
    "table_name":"table_constraints",
    "table_type":"VIEW",
    "created":1765009795837
  },
  {
    "table_catalog":"angad_kumar91",
    "table_schema":"information_schema",
    "table_name":"parameters",
    "table_type":"VIEW",
    "created":1765009795766
  },
  {
    "table_catalog":"angad_kumar91",
    "table_schema":"information_schema",
    "table_name":"volume_tags",
    "table_type":"VIEW",
    "created":1765009796107
  },
  {
    "table_catalog":"angad_kumar91",
    "table_schema":"information_schema",
    "table_name":"key_column_usage",
    "table_type":"VIEW",
    "created":1765009795854
  },
  {
    "table_catalog":"angad_kumar91",
    "table_schema":"information_schema",
    "table_name":"schema_privileges",
    "table_type":"VIEW",
    "created":1765009795803
  },
  {
    "table_catalog":"angad_kumar91",
    "table_schema":"information_schema",
    "table_name":"schemata",
    "table_type":"VIEW",
    "created":1765009795820
  },
  {
    "table_catalog":"angad_kumar91",
    "table_schema":"information_schema",
    "table_name":"schema_tags",
    "table_type":"VIEW",
    "created":1765009796056
  },
  {
    "table_catalog":"angad_kumar91",
    "table_schema":"information_schema",
    "table_name":"row_filters",
    "table_type":"VIEW",
    "created":1765009795968
  },
  {
    "table_catalog":"angad_kumar91",
    "table_schema":"information_schema",
    "table_name":"routine_privileges",
    "table_type":"VIEW",
    "created":1765009795785
  },
  {
    "table_catalog":"angad_kumar91",
    "table_schema":"information_schema",
    "table_name":"table_privileges",
    "table_type":"VIEW",
    "created":1765009795907
  },
  {
    "table_catalog":"angad_kumar91",
    "table_schema":"information_schema",
    "table_name":"information_schema_catalog_name",
    "table_type":"VIEW",
    "created":1765009795691
  },
  {
    "table_catalog":"angad_kumar91",
    "table_schema":"information_schema",
    "table_name":"column_tags",
    "table_type":"VIEW",
    "created":1765009796090
  },
  {
    "table_catalog":"angad_kumar91",
    "table_schema":"information_schema",
    "table_name":"table_tags",
    "table_type":"VIEW",
    "created":1765009796073
  },
  {
    "table_catalog":"angad_kumar91",
    "table_schema":"information_schema",
    "table_name":"volumes",
    "table_type":"VIEW",
    "created":1765009796004
  },
  {
    "table_catalog":"angad_kumar91",
    "table_schema":"information_schema",
    "table_name":"catalog_tags",
    "table_type":"VIEW",
    "created":1765009796039
  },
  {
    "table_catalog":"angad_kumar91",
    "table_schema":"information_schema",
    "table_name":"column_masks",
    "table_type":"VIEW",
    "created":1765009795985
  },
  {
    "table_catalog":"angad_kumar91",
    "table_schema":"information_schema",
    "table_name":"constraint_table_usage",
    "table_type":"VIEW",
    "created":1765009795890
  },
  {
    "table_catalog":"angad_kumar91",
    "table_schema":"information_schema",
    "table_name":"routine_columns",
    "table_type":"VIEW",
    "created":1765009795746
  },
  {
    "table_catalog":"angad_kumar91",
    "table_schema":"information_schema",
    "table_name":"catalogs",
    "table_type":"VIEW",
    "created":1765009795632
  },
  {
    "table_catalog":"angad_kumar91",
    "table_schema":"information_schema",
    "table_name":"columns",
    "table_type":"VIEW",
    "created":1765009795669
  },
  {
    "table_catalog":"angad_kumar91",
    "table_schema":"information_schema",
    "table_name":"constraint_column_usage",
    "table_type":"VIEW",
    "created":1765009795873
  },
  {
    "table_catalog":"angad_kumar91",
    "table_schema":"information_schema",
    "table_name":"volume_privileges",
    "table_type":"VIEW",
    "created":1765009796022
  },
  {
    "table_catalog":"angad_kumar91",
    "table_schema":"information_schema",
    "table_name":"routines",
    "table_type":"VIEW",
    "created":1765009795724
  },
  {
    "table_catalog":"angad_kumar91",
    "table_schema":"information_schema",
    "table_name":"check_constraints",
    "table_type":"VIEW",
    "created":1765009795650
  },
  {
    "table_catalog":"angad_kumar91",
    "table_schema":"information_schema",
    "table_name":"catalog_privileges",
    "table_type":"VIEW",
    "created":1765009795614
  }
]